pdfghost/__init__.py
tests/__init__.py
tests/test_batch_process.py
tests/test_compress.py
tests/test_encryption.py
tests/test_extract.py
tests/test_html_convert.py
tests/test_image_convert.py
tests/test_inserter.py
tests/test_merger.py
tests/test_page_number.py
tests/test_pdf_compare.py
tests/test_pdf_signing.py
tests/test_rearranger.py
tests/test_remover.py
tests/test_rotate.py
tests/test_rtf_convert.py
tests/test_splitter.py
tests/test_watermark.py
pdf_ghost-0.1.0.dist-info/LICENSE
pdf_ghost-0.1.0.dist-info/METADATA
pdf_ghost-0.1.0.dist-info/WHEEL
pdf_ghost-0.1.0.dist-info/top_level.txt
pdf_ghost-0.1.0.dist-info/RECORD
