Metadata-Version: 2.2
Name: pdf-ghost
Version: 0.1.0
Summary: for performing a wide range of operations on PDF files, including merging, splitting, rotating, compressing, watermarking, converting, encrypting/decrypting, extracting text/images, adding page numbers, batch processing, and comparing PDFs. It also supports generating PDFs from Markdown or LaTeX files.
Home-page: https://github.com/imshahinul/pdfghost
Author: S M Shahinul Islam
Author-email: s.m.shahinul.islam@gmail.com@gmail.com
Classifier: Programming Language :: Python :: 3
Classifier: License :: OSI Approved :: MIT License
Classifier: Operating System :: OS Independent
Requires-Python: >=3.7
License-File: LICENSE
Requires-Dist: cffi==1.17.1
Requires-Dist: chardet==5.2.0
Requires-Dist: charset-normalizer==3.4.1
Requires-Dist: cryptography==44.0.1
Requires-Dist: pdfminer.six==20231228
Requires-Dist: pdfplumber==0.11.5
Requires-Dist: pillow==11.1.0
Requires-Dist: pycparser==2.22
Requires-Dist: PyMuPDF==1.25.3
Requires-Dist: PyPDF2==3.0.1
Requires-Dist: pypdfium2==4.30.1
Requires-Dist: reportlab==4.3.0
Requires-Dist: termcolor==2.5.0
Dynamic: author
Dynamic: author-email
Dynamic: classifier
Dynamic: description
Dynamic: description-content-type
Dynamic: home-page
Dynamic: requires-dist
Dynamic: requires-python
Dynamic: summary
